 <?xml version="1.0" encoding="utf-8"?>
<game xmlns:xsi="http://www.w3.org/2001/XMLSchema-instance"
	xmlns:xsd="http://www.w3.org/2001/XMLSchema"
	name="Grifters - The Dystopian Universe"
	id="a383f475-2c20-47c7-9a79-4c2b57467775"
	octgnVersion="3.1.162.361"
	scriptVersion="3.1.0.2"
	version="0.0.0.1"
	markersize="NEEDVALUE"
	tags="Grifters"
	description="Grifters: Description here!"
	seturl="NEEDVALUE"
	gameurl="NEEDVALUE"
	authors="Brahyt"
	iconurl="NEEDVALUE">
	<scripts>
		<script src="scripts/actions.py" />
	</scripts>
	<card back="NEEDVALUE" front="NEEDVALUE" width="NEEDVALUE" height="NEEDVALUE" cornerRadius="NEEDVALUE">
		<property name="Quantity" type="String" hidden="false" ignoreText="False" />
		<property name="Subtitle" type="String" hidden="false" ignoreText="False" />
		<property name="Text" type="String" hidden="false" ignoreText="False" />
		<property name="Subtext" type="String" hidden="false" ignoreText="False" />
		<property name="Skilltype" type="String" hidden="false" ignoreText="False" />
	</card>
